cyberkit/arp_spoofer.py
cyberkit/cli.py
cyberkit/dns_spoofer.py
cyberkit/mac_changer.py
cyberkit/net_cut.py
cyberkit/network_scanner.py
cyberkit/packet_sniffer.py
cyberkit-0.1.0.dist-info/METADATA
cyberkit-0.1.0.dist-info/WHEEL
cyberkit-0.1.0.dist-info/entry_points.txt
cyberkit-0.1.0.dist-info/RECORD
