Metadata-Version: 2.3
Name: cyberkit
Version: 0.1.0
Summary: Pentesting tools made with Python.
License: GNU GPLv3
Author: Oliver Potter
Author-email: pypi@opott.uk
Requires-Python: >=3.13,<4
Classifier: License :: Other/Proprietary License
Classifier: Programming Language :: Python :: 3
Classifier: Programming Language :: Python :: 3.13
Requires-Dist: netfilterqueue (>=1.1.0,<2.0.0)
Requires-Dist: scapy (>=2.6.1,<3.0.0)
